sppga/core/__init__.py
sppga/core/main.py
sppga-0.0.6.dist-info/METADATA
sppga-0.0.6.dist-info/WHEEL
sppga-0.0.6.dist-info/top_level.txt
sppga-0.0.6.dist-info/RECORD
