Metadata-Version: 2.1
Name: sppga
Version: 0.0.6
Summary: Scaffold Python Package Github Actions
Home-page: UNKNOWN
Author: Johni Douglas Marangon
License: UNKNOWN
Platform: UNKNOWN
Classifier: Programming Language :: Python :: 3
Classifier: Operating System :: OS Independent
Requires-Python: >=3
Requires-Dist: requests
